mkdocs_dataview/__init__.py
mkdocs_dataview/__main__.py
mkdocs_dataview/plugin.py
mkdocs_dataview/utils.py
mkdocs_dataview-0.0.2.dist-info/licenses/LICENSE
mkdocs_dataview-0.0.2.dist-info/METADATA
mkdocs_dataview-0.0.2.dist-info/WHEEL
mkdocs_dataview-0.0.2.dist-info/entry_points.txt
mkdocs_dataview-0.0.2.dist-info/top_level.txt
mkdocs_dataview-0.0.2.dist-info/RECORD
