Metadata-Version: 2.4
Name: mkdocs-dataview
Version: 0.0.2
Summary: A mkdocs plugin inspired by dataview plugin in Obsidian
Author-email: Alexander Nevskiy <kepkin@gmail.com>
Classifier: Programming Language :: Python :: 3
Classifier: Operating System :: OS Independent
Classifier: License :: OSI Approved :: MIT License
Requires-Python: >=3.8
License-File: LICENSE
Requires-Dist: dictquery==0.5.0
Requires-Dist: python-frontmatter==1.1.0
Requires-Dist: mkdocs==1.5.3
Dynamic: license-file
